checkpkgaudit
