Metadata-Version: 1.1
Name: checkpkgaudit
Version: 0.3
Summary: Check FreeBSD pkg audit Nagios|Icinga|shinken|etc plugin.
Home-page: https://github.com/jpcw/check_pkgaudit
Author: Jean-Philippe Camguilhem
Author-email: jp.camguilhem__at__gmail.com
License: BSD
Keywords: Nagios Icinga plugin check pkg audit monitoring
Platform: any
Classifier: Programming Language :: Python
Classifier: License :: OSI Approved :: BSD License
Classifier: Development Status :: 5 - Production/Stable
Classifier: Environment :: Plugins
Classifier: Intended Audience :: Developers
Classifier: Intended Audience :: System Administrators
Classifier: Operating System :: POSIX :: BSD :: FreeBSD
Classifier: Programming Language :: Python :: 2.6
Classifier: Programming Language :: Python :: 2.7
Classifier: Programming Language :: Python :: 3.2
Classifier: Programming Language :: Python :: 3.3
Classifier: Programming Language :: Python :: 3.4
Classifier: Programming Language :: Python :: Implementation :: CPython
Classifier: Programming Language :: Python :: Implementation :: PyPy
Classifier: Topic :: Software Development :: Libraries :: Python Modules
Classifier: Topic :: System :: Monitoring
